sat_toolkit-0.5.0.dist-info/WHEEL
sat_toolkit-0.5.0.dist-info/LICENSE
sat_toolkit-0.5.0.dist-info/top_level.txt
sat_toolkit-0.5.0.dist-info/RECORD
sat_toolkit-0.5.0.dist-info/METADATA
sat_toolkit/formula.pyi
sat_toolkit/py.typed
sat_toolkit/util.py
sat_toolkit/__init__.py
sat_toolkit/formula.cpython-39-x86_64-linux-gnu.so
