Metadata-Version: 2.1
Name: sat-toolkit
Version: 0.5.0
Summary: Tool for manipulating CNF formulas
Home-page: https://github.com/fanosta/sat_toolkit
Author: Marcel Nageler
Author-email: marcel.nageler@iaik.tugraz.at
Classifier: Programming Language :: Python :: 3
Classifier: License :: OSI Approved :: MIT License
Classifier: Operating System :: POSIX :: Linux
License-File: LICENSE
Requires-Dist: numpy >=1.21
